enhaaancedLists.py
enhaaancedLists-0.90.dist-info/LICENSE
enhaaancedLists-0.90.dist-info/METADATA
enhaaancedLists-0.90.dist-info/WHEEL
enhaaancedLists-0.90.dist-info/top_level.txt
enhaaancedLists-0.90.dist-info/RECORD
