Metadata-Version: 2.1
Name: enhaaancedLists
Version: 0.90
Summary: (Thread-safe) list(s) with extended / enhanced in-place capabilities (e.g. conditional element selection)
Home-page: https://www.blackward.de
Author: Dominik Niedenzu
Author-email: pyadaaah@blackward.de
Maintainer: Dominik Niedenzu
License: Proprietary License
Platform: any platform which provides python
Classifier: Development Status :: 4 - Beta
Classifier: Intended Audience :: Developers
Classifier: Intended Audience :: Education
Classifier: Intended Audience :: Science/Research
Classifier: Intended Audience :: Other Audience
Classifier: License :: Other/Proprietary License
Classifier: Operating System :: OS Independent
Classifier: Programming Language :: Python
Classifier: Topic :: Software Development
Requires-Python: >= 2.2
License-File: LICENSE
